LICENSE
MANIFEST.in
README.rst
setup.cfg
setup.py
artellapipe/__init__.py
artellapipe/tools/__init__.py
artellapipe/tools/welcome/__init__.py
artellapipe/tools/welcome/__logging__.ini
artellapipe/tools/welcome/__version__.py
artellapipe/tools/welcome/welcome.py
artellapipe_tools_welcome.egg-info/PKG-INFO
artellapipe_tools_welcome.egg-info/SOURCES.txt
artellapipe_tools_welcome.egg-info/dependency_links.txt
artellapipe_tools_welcome.egg-info/not-zip-safe
artellapipe_tools_welcome.egg-info/requires.txt
artellapipe_tools_welcome.egg-info/top_level.txt
tests/__init__.py
tests/test_welcome.py