Metadata-Version: 2.1
Name: artellapipe-tools-welcome
Version: 0.0.7
Summary: Tool that shows useful information for the current Artella project
Home-page: https://github.com/ArtellaPipe/artellapipe-tools-welcome
Author: Tomas Poveda
Author-email: tpovedatd@gmail.com
License: MIT
Platform: UNKNOWN
Provides-Extra: dev
Provides-Extra: test
